{
    "tests": [
        {
            "id": "test2",
            "name": "My Test",
            "browser": "PhantomJS",
            "status": false,
            "passedAssertions": 0,
            "failedAssertions": 12,
            "actions": [
                {
                    "value": "http://www.247blinds.co.uk/ecowood-pure-white-venetian-blind",
                    "type": "open",
                    "uuid": "uuid-43",
                    "kind": "action"
                },
                {
                    "value": ".field-label-width",
                    "type": "type",
                    "uuid": "uuid-44",
                    "kind": "action"
                },
                {
                    "value": ".field-label-drop",
                    "type": "type",
                    "uuid": "uuid-45",
                    "kind": "action"
                },
                {
                    "value": ".btn-get-price",
                    "type": "click",
                    "uuid": "uuid-46",
                    "kind": "action"
                },
                {
                    "value": "1000 ms",
                    "type": "wait",
                    "uuid": "uuid-47",
                    "kind": "action"
                },
                {
                    "success": false,
                    "expected": "a",
                    "value": "Ecowood, Pure White - Venetian Blind",
                    "type": "text",
                    "kind": "assertion"
                },
                {
                    "success": false,
                    "expected": "1",
                    "value": "£41.58",
                    "type": "text",
                    "kind": "assertion"
                },
                {
                    "value": "http://www.247blinds.co.uk/origin-bright-white-venetian-blind",
                    "type": "open",
                    "uuid": "uuid-48",
                    "kind": "action"
                },
                {
                    "value": ".field-label-width",
                    "type": "type",
                    "uuid": "uuid-49",
                    "kind": "action"
                },
                {
                    "value": ".field-label-drop",
                    "type": "type",
                    "uuid": "uuid-50",
                    "kind": "action"
                },
                {
                    "value": ".btn-get-price",
                    "type": "click",
                    "uuid": "uuid-51",
                    "kind": "action"
                },
                {
                    "value": "1000 ms",
                    "type": "wait",
                    "uuid": "uuid-52",
                    "kind": "action"
                },
                {
                    "success": false,
                    "expected": "a",
                    "value": "Origin, Bright White - Venetian Blind",
                    "type": "text",
                    "kind": "assertion"
                },
                {
                    "success": false,
                    "expected": "1",
                    "value": "£47.03",
                    "type": "text",
                    "kind": "assertion"
                },
                {
                    "value": "http://www.247blinds.co.uk/origin-basic-white-venetian-blind",
                    "type": "open",
                    "uuid": "uuid-53",
                    "kind": "action"
                },
                {
                    "value": ".field-label-width",
                    "type": "type",
                    "uuid": "uuid-54",
                    "kind": "action"
                },
                {
                    "value": ".field-label-drop",
                    "type": "type",
                    "uuid": "uuid-55",
                    "kind": "action"
                },
                {
                    "value": ".btn-get-price",
                    "type": "click",
                    "uuid": "uuid-56",
                    "kind": "action"
                },
                {
                    "value": "1000 ms",
                    "type": "wait",
                    "uuid": "uuid-57",
                    "kind": "action"
                },
                {
                    "success": false,
                    "expected": "a",
                    "value": "Origin, Basic White - Venetian Blind",
                    "type": "text",
                    "kind": "assertion"
                },
                {
                    "success": false,
                    "expected": "1",
                    "value": "£27.77",
                    "type": "text",
                    "kind": "assertion"
                },
                {
                    "value": "http://www.247blinds.co.uk/mayfair-white-roman-blind",
                    "type": "open",
                    "uuid": "uuid-58",
                    "kind": "action"
                },
                {
                    "value": ".field-label-width",
                    "type": "type",
                    "uuid": "uuid-59",
                    "kind": "action"
                },
                {
                    "value": ".field-label-drop",
                    "type": "type",
                    "uuid": "uuid-60",
                    "kind": "action"
                },
                {
                    "value": ".btn-get-price",
                    "type": "click",
                    "uuid": "uuid-61",
                    "kind": "action"
                },
                {
                    "value": "1000 ms",
                    "type": "wait",
                    "uuid": "uuid-62",
                    "kind": "action"
                },
                {
                    "success": false,
                    "expected": "a",
                    "value": "Mayfair, White - Roman Blind",
                    "type": "text",
                    "kind": "assertion"
                },
                {
                    "success": false,
                    "expected": "1",
                    "value": "£47.24",
                    "type": "text",
                    "kind": "assertion"
                },
                {
                    "value": "http://www.247blinds.co.uk/rimini-white-roller-blind",
                    "type": "open",
                    "uuid": "uuid-63",
                    "kind": "action"
                },
                {
                    "value": ".field-label-width",
                    "type": "type",
                    "uuid": "uuid-64",
                    "kind": "action"
                },
                {
                    "value": ".field-label-drop",
                    "type": "type",
                    "uuid": "uuid-65",
                    "kind": "action"
                },
                {
                    "value": ".btn-get-price",
                    "type": "click",
                    "uuid": "uuid-66",
                    "kind": "action"
                },
                {
                    "value": "1000 ms",
                    "type": "wait",
                    "uuid": "uuid-67",
                    "kind": "action"
                },
                {
                    "success": false,
                    "expected": "a",
                    "value": "Rimini, White - Roller Blind",
                    "type": "text",
                    "kind": "assertion"
                },
                {
                    "success": false,
                    "expected": "1",
                    "value": "£25.58",
                    "type": "text",
                    "kind": "assertion"
                },
                {
                    "value": "http://www.247blinds.co.uk/marill-ivory-roller-blind",
                    "type": "open",
                    "uuid": "uuid-68",
                    "kind": "action"
                },
                {
                    "value": ".field-label-width",
                    "type": "type",
                    "uuid": "uuid-69",
                    "kind": "action"
                },
                {
                    "value": ".field-label-drop",
                    "type": "type",
                    "uuid": "uuid-70",
                    "kind": "action"
                },
                {
                    "value": ".btn-get-price",
                    "type": "click",
                    "uuid": "uuid-71",
                    "kind": "action"
                },
                {
                    "value": "1000 ms",
                    "type": "wait",
                    "uuid": "uuid-72",
                    "kind": "action"
                },
                {
                    "success": false,
                    "expected": "a",
                    "value": "Marill, Ivory - Roller Blind",
                    "type": "text",
                    "kind": "assertion"
                },
                {
                    "success": false,
                    "expected": "1",
                    "value": "£32.93",
                    "type": "text",
                    "kind": "assertion"
                }
            ]
        }
    ],
    "elapsedTime": {
        "seconds": 14.109768431
    },
    "status": false,
    "assertions": 12,
    "assertionsFailed": 12,
    "assertionsPassed": 0
}